d3c_polyskel/__init__.py
d3c_polyskel/polyskel.py
d3c_polyskel-0.1.0.dist-info/licenses/LICENSE
d3c_polyskel-0.1.0.dist-info/METADATA
d3c_polyskel-0.1.0.dist-info/WHEEL
d3c_polyskel-0.1.0.dist-info/top_level.txt
d3c_polyskel-0.1.0.dist-info/RECORD
