Metadata-Version: 2.4
Name: d3c-polyskel
Version: 0.1.0
Summary: A library to compute the straight skeleton of a shape.
Author-email: D3Companion GmbH <contact@d3companion.com>
License: LGPL-3.0-or-later
Project-URL: Homepage, https://github.com/D3Companion/d3c-polyskel
Requires-Python: >=3.8
License-File: LICENSE
Requires-Dist: euclid3>=0.01
Requires-Dist: Pillow>=12.0.0
Dynamic: license-file
